MensajesPruebaRene2-9.0.data/scripts/test.py
mensajes/__init__.py
mensajes/adios/__init__.py
mensajes/adios/despedidas.py
mensajes/hola/__init__.py
mensajes/hola/saludos.py
MensajesPruebaRene2-9.0.dist-info/LICENSE
MensajesPruebaRene2-9.0.dist-info/METADATA
MensajesPruebaRene2-9.0.dist-info/WHEEL
MensajesPruebaRene2-9.0.dist-info/top_level.txt
MensajesPruebaRene2-9.0.dist-info/RECORD
